bitfielddraw
